ktbench/__init__.py
ktbench/cloud_handler.py
ktbench/config.py
ktbench/pad_utils.py
ktbench/run.py
ktbench/trainlogs.py
ktbench/datapipeline/__init__.py
ktbench/datapipeline/dataset_map_utils.py
ktbench/datapipeline/middata_manager.py
ktbench/datapipeline/pipeline.py
ktbench/model/__init__.py
ktbench/model/basemodel.py
ktbench/model/dkt_related/__init__.py
ktbench/model/dkt_related/autoregressive_decoding_dkt.py
ktbench/model/dkt_related/dkt.py
ktbench/model/dkt_related/fuse_dkt.py
ktbench/model/dkt_related/label_mask_dkt.py
ktbench/model/dkt_related/step_dkt.py
ktbench/train/__init__.py
ktbench/train/train.py
ktbench-0.0.2.dist-info/METADATA
ktbench-0.0.2.dist-info/NOTICE.txt
ktbench-0.0.2.dist-info/WHEEL
ktbench-0.0.2.dist-info/top_level.txt
ktbench-0.0.2.dist-info/RECORD
